LICENSE
MANIFEST.in
README.rst
setup.cfg
setup.py
versioneer.py
koala_html.egg-info/PKG-INFO
koala_html.egg-info/SOURCES.txt
koala_html.egg-info/dependency_links.txt
koala_html.egg-info/entry_points.txt
koala_html.egg-info/top_level.txt
src/__init__.py
src/_version.py
src/simple_style.css
src/table.py