Metadata-Version: 1.1
Name: koala-html
Version: 0.1.0
Summary: A simple HTML page generator
Home-page: https://github.com/GregoryAshton/koala_html
Author: Greg Ashton
Author-email: gregory.ashton@ligo.org
License: MIT
Platform: UNKNOWN
Classifier: Programming Language :: Python :: 3.7
Classifier: License :: OSI Approved :: MIT License
Classifier: Operating System :: OS Independent
